{"noiseKey":{"private":{"type":"Buffer","data":"+Ngs1lRXC4KsxlgGc6h4S5QzlSdTTHTCdQPeeD8P2Fg="},"public":{"type":"Buffer","data":"U6Cq59x1tDX5dMtLQ458rdBkeriOBdL+dnw56C/mhAI="}},"pairingEphemeralKeyPair":{"private":{"type":"Buffer","data":"+Iv7tuZUCLwglrZeQqFZie7GeLsGj+HddfbffHD8FE0="},"public":{"type":"Buffer","data":"iOMVf8ZlK+L8ySZodGJiNwAVTWA7FQ7vfl60kU5MWyI="}},"signedIdentityKey":{"private":{"type":"Buffer","data":"8DO5Grj9JNwVssQKxS+WGJ6GyIVIKUxtIIX4uK2sQWw="},"public":{"type":"Buffer","data":"qo6ZGapQ4qx3SLAeUKSKdFE5qk8IwOKNULchmLF9vzs="}},"signedPreKey":{"keyPair":{"private":{"type":"Buffer","data":"SKMvbKkfBuz4IA95zbu/s8qhtMbwJUzhmeuwpCJfS28="},"public":{"type":"Buffer","data":"K4KCB/w9/M+X0PdC5TqmiiaCUahmurnM9zDFQh3SWF0="}},"signature":{"type":"Buffer","data":"T0+uqSzRejnxyLxDY8VcmBnff/7O8qsD6JKZfiJPfZn8ewG9b9sfoXeea2kvlynQMqkxYID3VyFYFKOqBA2vCQ=="},"keyId":1},"registrationId":136,"advSecretKey":"VUFCDhvnV/kZnDGc0mycVRQhBnmz1ladtoCsw434Dcg=","processedHistoryMessages":[{"key":{"remoteJid":"917510975208@s.whatsapp.net","fromMe":true,"id":"DA3A1398B298C503D1CF74DD725960E1"},"messageTimestamp":1757869050},{"key":{"remoteJid":"917510975208@s.whatsapp.net","fromMe":true,"id":"1B3177559599C2ED71A41059609D0B6E"},"messageTimestamp":1757869058},{"key":{"remoteJid":"917510975208@s.whatsapp.net","fromMe":true,"id":"DB2742258EBDFF731F03E91E6CB8A7A4"},"messageTimestamp":1757869083},{"key":{"remoteJid":"917510975208@s.whatsapp.net","fromMe":true,"id":"DB09182A580A13A7FAFFEEFB0A731F60"},"messageTimestamp":1757869096},{"key":{"remoteJid":"917510975208@s.whatsapp.net","fromMe":true,"id":"513BD1036CF8E224B3AB7241F4495ECC"},"messageTimestamp":1757869108},{"key":{"remoteJid":"917510975208@s.whatsapp.net","fromMe":true,"id":"144C1E977CF48DA278E1B33F8BDECAEA"},"messageTimestamp":1757869120},{"key":{"remoteJid":"917510975208@s.whatsapp.net","fromMe":true,"id":"A04613DFC2DA4F86ED10421F9E45BEA2"},"messageTimestamp":1757869132},{"key":{"remoteJid":"917510975208@s.whatsapp.net","fromMe":true,"id":"C65090A92A1869D5CC20E82434BB9316"},"messageTimestamp":1757869147},{"key":{"remoteJid":"917510975208@s.whatsapp.net","fromMe":true,"id":"368553C549F5B333DB5145D8CE05E75E"},"messageTimestamp":1757869154},{"key":{"remoteJid":"917510975208@s.whatsapp.net","fromMe":true,"id":"83ACD983D9590652D367DCA0136EADE6"},"messageTimestamp":1757869166},{"key":{"remoteJid":"917510975208@s.whatsapp.net","fromMe":true,"id":"E52D8474E8FC28D28F6F417EC9B883BF"},"messageTimestamp":1757869176},{"key":{"remoteJid":"917510975208@s.whatsapp.net","fromMe":true,"id":"CD9E83941FFA8C87D52DDA6771BC386A"},"messageTimestamp":1757869189},{"key":{"remoteJid":"917510975208@s.whatsapp.net","fromMe":true,"id":"36285F841CAE0A010DC4E847BB56667A"},"messageTimestamp":1757869208},{"key":{"remoteJid":"917510975208@s.whatsapp.net","fromMe":true,"id":"86688B57AA2CC04C344E6393C176E616"},"messageTimestamp":1757869217},{"key":{"remoteJid":"917510975208@s.whatsapp.net","fromMe":true,"id":"8EDFF10D67D51938D5E96E6FF07EA9FA"},"messageTimestamp":1757869234},{"key":{"remoteJid":"917510975208@s.whatsapp.net","fromMe":true,"id":"FC240156732B6925C0B2857CA31CB397"},"messageTimestamp":1757869256},{"key":{"remoteJid":"917510975208@s.whatsapp.net","fromMe":true,"id":"2A255FD05D0EE02A11B5F9B925A2A76F"},"messageTimestamp":1757869282},{"key":{"remoteJid":"917510975208@s.whatsapp.net","fromMe":true,"id":"743D645221B926AE1855A95CF002F1A5"},"messageTimestamp":1757869295},{"key":{"remoteJid":"917510975208@s.whatsapp.net","fromMe":true,"id":"0750DB290BCBAEB9E54D553090A49FC6"},"messageTimestamp":1757869312},{"key":{"remoteJid":"917510975208@s.whatsapp.net","fromMe":true,"id":"CFD15AE075AD97F4552651874AA590A0"},"messageTimestamp":1757869325},{"key":{"remoteJid":"917510975208@s.whatsapp.net","fromMe":true,"id":"986772E7D31420BE72272408C70F277E"},"messageTimestamp":1757869336},{"key":{"remoteJid":"917510975208@s.whatsapp.net","fromMe":true,"id":"EA6279E4D484C33F418B664B39932CF9"},"messageTimestamp":1757869351},{"key":{"remoteJid":"917510975208@s.whatsapp.net","fromMe":true,"id":"9676965C15C2227610AD62AF4255D81C"},"messageTimestamp":1757869370},{"key":{"remoteJid":"917510975208@s.whatsapp.net","fromMe":true,"id":"2EB6C6562D9B24BF3DD7840A295BE6D5"},"messageTimestamp":1757869386},{"key":{"remoteJid":"917510975208@s.whatsapp.net","fromMe":true,"id":"2A574E9C4E5DB7A20574CF1628106D52"},"messageTimestamp":1757869401},{"key":{"remoteJid":"917510975208@s.whatsapp.net","fromMe":true,"id":"C11E159A8D2AA127B9CEDC0902E58268"},"messageTimestamp":1757869425},{"key":{"remoteJid":"917510975208@s.whatsapp.net","fromMe":true,"id":"29743521F767A7B481528EAE38F20A50"},"messageTimestamp":1757869447},{"key":{"remoteJid":"917510975208@s.whatsapp.net","fromMe":true,"id":"4EE15C132A366CDB011EBFCB5AA117DE"},"messageTimestamp":1757869462}],"nextPreKeyId":34,"firstUnuploadedPreKeyId":34,"accountSyncCounter":1,"accountSettings":{"unarchiveChats":false},"deviceId":"CM68m3uvTfK-E3f5liDzjg","phoneId":"41bdede3-379c-4a99-b2fb-17459b4eb7c5","identityId":{"type":"Buffer","data":"gUxCb/l6Z9k0+8lTIcdFqOMgOfA="},"registered":true,"backupToken":{"type":"Buffer","data":"+KG4u7NqIDxieHsNJQnCpn+9QTk="},"registration":{},"pairingCode":"DG3EFGV5","me":{"id":"917510975208:21@s.whatsapp.net","lid":"254713236877488:21@lid","name":"🥶"},"account":{"details":"CO6bq30Q5OebxgYYASAAKAA=","accountSignatureKey":"e3XSHYA9Xei0+O09LamaGtEXmg+pcuc3mj1VOZ2wkyI=","accountSignature":"O7pyChuPb+lg/DY5tQkZSLCsG3eNL7uLeVWumr3jtL6s1cSpjI3z0xunTnnKaErGHAFx9wiasHPW4pTSE5keCw==","deviceSignature":"LNHTHO+Maqb4vB9CfO3xOYJCawS8ujN8i6l4ea9CPlG7RhPKRZFKa/q0nHkhw9WG5H8VRGwGi89FFPVwgZquAQ=="},"signalIdentities":[{"identifier":{"name":"917510975208:21@s.whatsapp.net","deviceId":0},"identifierKey":{"type":"Buffer","data":"BXt10h2APV3otPjtPS2pmhrRF5oPqXLnN5o9VTmdsJMi"}}],"platform":"android","routingInfo":{"type":"Buffer","data":"CAUIAg=="},"lastAccountSyncTimestamp":1757869043,"lastPropHash":"3fYwCK","myAppStateKeyId":"AAAAAKFo"}