{"noiseKey":{"private":{"type":"Buffer","data":"8AsFaLCDoN2i9uomJjM3156Yf8J+ZZl6jGcxCovUf1Q="},"public":{"type":"Buffer","data":"fWjYf/Au4WECPRYuSteIny/rH/YlCT2YIjTExQl6bwo="}},"pairingEphemeralKeyPair":{"private":{"type":"Buffer","data":"SAr9NTKNUcBEjoePrmMhCWgM0f1wcVbx+GdkUNHpaXY="},"public":{"type":"Buffer","data":"5SB7i0mmkGvgcmcjFHrG0FEyHSonfl6sAR0gwEgr+CM="}},"signedIdentityKey":{"private":{"type":"Buffer","data":"EOAv/eDFgJjytumlJA7pYPnROcZVUHKtepHgY2TUQXo="},"public":{"type":"Buffer","data":"Mtog/9CnZfT1Kj/REHCKeSWCuYB3nDa6x+q2BlwbIns="}},"signedPreKey":{"keyPair":{"private":{"type":"Buffer","data":"mOHlqJiXnreeOzeNdljyb8KG67hC0Gbvd34w7jSmPlM="},"public":{"type":"Buffer","data":"3SdiDm+Rj5GySd8IxmHm/o6mu486sIAdZDxjeUat51c="}},"signature":{"type":"Buffer","data":"cPpWgJXPAhM4tXqI8mQ/fbes8PUkfJ7hHfyjvyYbJ0BUF8SCcQ0woo8h/DrN0MYUita4Yx8MxuSVvY39307vig=="},"keyId":1},"registrationId":230,"advSecretKey":"bNHVbfxy1H+xDtpxuSxWkh8hCf7cGJj8R1O8/ci1xC4=","processedHistoryMessages":[{"key":{"remoteJid":"923044314089@s.whatsapp.net","fromMe":true,"id":"696CA96098C72F10DD916410505990E6"},"messageTimestamp":1757800010},{"key":{"remoteJid":"923044314089@s.whatsapp.net","fromMe":true,"id":"E48CAA1193C8C4D68EF6DFC864276987"},"messageTimestamp":1757800017},{"key":{"remoteJid":"923044314089@s.whatsapp.net","fromMe":true,"id":"F64828E0613D2291C065E12137273DBF"},"messageTimestamp":1757800038},{"key":{"remoteJid":"923044314089@s.whatsapp.net","fromMe":true,"id":"AF3ED3BF05C85A50B42053E382A6D329"},"messageTimestamp":1757800043},{"key":{"remoteJid":"923044314089@s.whatsapp.net","fromMe":true,"id":"B7F7E0AEE7F78B212A993618A7B0BDB0"},"messageTimestamp":1757800052},{"key":{"remoteJid":"923044314089@s.whatsapp.net","fromMe":true,"id":"165C1AF359A8379ADA68CAC0B7379F5C"},"messageTimestamp":1757800070},{"key":{"remoteJid":"923044314089@s.whatsapp.net","fromMe":true,"id":"03528A190F29102B2DA31AFD0C28A9C9"},"messageTimestamp":1757800078},{"key":{"remoteJid":"923044314089@s.whatsapp.net","fromMe":true,"id":"0BBDF90E89E8390BC76BA3693E7C26BF"},"messageTimestamp":1757800085},{"key":{"remoteJid":"923044314089@s.whatsapp.net","fromMe":true,"id":"2940AB948FFF8C8FF9D51A986FEA7939"},"messageTimestamp":1757800096},{"key":{"remoteJid":"923044314089@s.whatsapp.net","fromMe":true,"id":"CA5C6726E71CB9F30DFCA03B4CC58B65"},"messageTimestamp":1757800110},{"key":{"remoteJid":"923044314089@s.whatsapp.net","fromMe":true,"id":"EE6D35DF627E63528A03ECDCA5D33927"},"messageTimestamp":1757800122},{"key":{"remoteJid":"923044314089@s.whatsapp.net","fromMe":true,"id":"6806AA5488B468EC5A0E3C2434D1EF3D"},"messageTimestamp":1757800159},{"key":{"remoteJid":"923044314089@s.whatsapp.net","fromMe":true,"id":"0A4EEEC91F0D28D72F289BEAD0E999BB"},"messageTimestamp":1757800168},{"key":{"remoteJid":"923044314089@s.whatsapp.net","fromMe":true,"id":"3135A4EDE0043FF7BDD78AB9108053BA"},"messageTimestamp":1757800179},{"key":{"remoteJid":"923044314089@s.whatsapp.net","fromMe":true,"id":"E5BA1F526F3C2589FEEFB1117ACA31AD"},"messageTimestamp":1757800192},{"key":{"remoteJid":"923044314089@s.whatsapp.net","fromMe":true,"id":"3D6A1D994A5D7B0C7E9CAE33185741EC"},"messageTimestamp":1757800198},{"key":{"remoteJid":"923044314089@s.whatsapp.net","fromMe":true,"id":"00F4732B11112B3E8B19A6F34C57340F"},"messageTimestamp":1757800211}],"nextPreKeyId":31,"firstUnuploadedPreKeyId":31,"accountSyncCounter":1,"accountSettings":{"unarchiveChats":false},"deviceId":"rQUh1K4BS9CGOWGoYQ3iRA","phoneId":"a63b4bf0-1fab-4ae3-a021-a235ec8e1db9","identityId":{"type":"Buffer","data":"t/f5+ogDEyraYUrhHveRDnabVIc="},"registered":true,"backupToken":{"type":"Buffer","data":"czgvC7e0veXRxoZexuMO3Ak+2+0="},"registration":{},"pairingCode":"APQSEZC2","me":{"id":"923044314089:28@s.whatsapp.net","lid":"252931077099745:28@lid","name":"🇩ɪᴍᴘʟᴇ 🇶ᴜᴇᴇɴ"},"account":{"details":"COmjrvkBEKnMl8YGGAEgACgA","accountSignatureKey":"6oZMFd1cGaIdsylAVY8NdtOl+0MSj02/9dTTkkHidWs=","accountSignature":"3ZMBqiW3pWt8hx2ohUHR+b1zAdBYJlq76OrwjRf2zo7AqTn0iVZdpCwejuDFq8DjtXVR5EhLaT/QB+zaZweMAg==","deviceSignature":"AM3LQZAqj9JzV9JWNDDgf/qvPM0MwsBepANu7Gu8E1u6d1CRZb0s25R7Y2wQocbEXrajz4UlfHKaBOK2pnXMgA=="},"signalIdentities":[{"identifier":{"name":"923044314089:28@s.whatsapp.net","deviceId":0},"identifierKey":{"type":"Buffer","data":"BeqGTBXdXBmiHbMpQFWPDXbTpftDEo9Nv/XU05JB4nVr"}}],"platform":"android","routingInfo":{"type":"Buffer","data":"CAIICA=="},"lastAccountSyncTimestamp":1757800000,"lastPropHash":"1K4hH4","myAppStateKeyId":"AAAAAA7v"}